{"nodes": [{"id": "apps", "label": "apps.py", "file_type": "code", "source_file": "backend/apps/recruitment/apps.py", "source_location": "L1"}, {"id": "apps_recruitmentconfig", "label": "RecruitmentConfig", "file_type": "code", "source_file": "backend/apps/recruitment/apps.py", "source_location": "L4"}, {"id": "appconfig", "label": "AppConfig", "file_type": "code", "source_file": "", "source_location": ""}], "edges": [{"source": "apps", "target": "django_apps", "relation": "imports_from", "confidence": "EXTRACTED", "source_file": "backend/apps/recruitment/apps.py", "source_location": "L1", "weight": 1.0}, {"source": "apps", "target": "apps_recruitmentconfig", "relation": "contains", "confidence": "EXTRACTED", "source_file": "backend/apps/recruitment/apps.py", "source_location": "L4", "weight": 1.0}, {"source": "apps_recruitmentconfig", "target": "appconfig", "relation": "inherits", "confidence": "EXTRACTED", "source_file": "backend/apps/recruitment/apps.py", "source_location": "L4", "weight": 1.0}]}