{"nodes": [{"id": "leave_approval_spec", "label": "leave-approval.spec.ts", "file_type": "code", "source_file": "frontend/e2e/employee/leave-approval.spec.ts", "source_location": "L1"}], "edges": [{"source": "leave_approval_spec", "target": "auth", "relation": "imports_from", "confidence": "EXTRACTED", "source_file": "frontend/e2e/employee/leave-approval.spec.ts", "source_location": "L1", "weight": 1.0}, {"source": "leave_approval_spec", "target": "helpers", "relation": "imports_from", "confidence": "EXTRACTED", "source_file": "frontend/e2e/employee/leave-approval.spec.ts", "source_location": "L2", "weight": 1.0}]}