{"nodes": [{"id": "event_stream", "label": "event_stream.py", "file_type": "code", "source_file": "backend/apps/biometrics/event_stream.py", "source_location": "L1"}, {"id": "event_stream_format_sse", "label": "_format_sse()", "file_type": "code", "source_file": "backend/apps/biometrics/event_stream.py", "source_location": "L29"}, {"id": "event_stream_attendanceeventstreamview", "label": "AttendanceEventStreamView", "file_type": "code", "source_file": "backend/apps/biometrics/event_stream.py", "source_location": "L34"}, {"id": "view", "label": "View", "file_type": "code", "source_file": "", "source_location": ""}, {"id": "event_stream_attendanceeventstreamview_get", "label": ".get()", "file_type": "code", "source_file": "backend/apps/biometrics/event_stream.py", "source_location": "L35"}, {"id": "event_stream_deviceeventstreamview", "label": "DeviceEventStreamView", "file_type": "code", "source_file": "backend/apps/biometrics/event_stream.py", "source_location": "L92"}, {"id": "event_stream_deviceeventstreamview_get", "label": ".get()", "file_type": "code", "source_file": "backend/apps/biometrics/event_stream.py", "source_location": "L93"}], "edges": [{"source": "event_stream", "target": "json", "relation": "imports", "confidence": "EXTRACTED", "source_file": "backend/apps/biometrics/event_stream.py", "source_location": "L3", "weight": 1.0}, {"source": "event_stream", "target": "logging", "relation": "imports", "confidence": "EXTRACTED", "source_file": "backend/apps/biometrics/event_stream.py", "source_location": "L4", "weight": 1.0}, {"source": "event_stream", "target": "django_http", "relation": "imports_from", "confidence": "EXTRACTED", "source_file": "backend/apps/biometrics/event_stream.py", "source_location": "L6", "weight": 1.0}, {"source": "event_stream", "target": "django_utils_decorators", "relation": "imports_from", "confidence": "EXTRACTED", "source_file": "backend/apps/biometrics/event_stream.py", "source_location": "L7", "weight": 1.0}, {"source": "event_stream", "target": "django_views_decorators_csrf", "relation": "imports_from", "confidence": "EXTRACTED", "source_file": "backend/apps/biometrics/event_stream.py", "source_location": "L8", "weight": 1.0}, {"source": "event_stream", "target": "django_views_generic", "relation": "imports_from", "confidence": "EXTRACTED", "source_file": "backend/apps/biometrics/event_stream.py", "source_location": "L9", "weight": 1.0}, {"source": "event_stream", "target": "apps_accounts_workspaces", "relation": "imports_from", "confidence": "EXTRACTED", "source_file": "backend/apps/biometrics/event_stream.py", "source_location": "L11", "weight": 1.0}, {"source": "event_stream", "target": "redis", "relation": "imports", "confidence": "EXTRACTED", "source_file": "backend/apps/biometrics/event_stream.py", "source_location": "L17", "weight": 1.0}, {"source": "event_stream", "target": "event_stream_format_sse", "relation": "contains", "confidence": "EXTRACTED", "source_file": "backend/apps/biometrics/event_stream.py", "source_location": "L29", "weight": 1.0}, {"source": "event_stream", "target": "event_stream_attendanceeventstreamview", "relation": "contains", "confidence": "EXTRACTED", "source_file": "backend/apps/biometrics/event_stream.py", "source_location": "L34", "weight": 1.0}, {"source": "event_stream_attendanceeventstreamview", "target": "view", "relation": "inherits", "confidence": "EXTRACTED", "source_file": "backend/apps/biometrics/event_stream.py", "source_location": "L34", "weight": 1.0}, {"source": "event_stream_attendanceeventstreamview", "target": "event_stream_attendanceeventstreamview_get", "relation": "method", "confidence": "EXTRACTED", "source_file": "backend/apps/biometrics/event_stream.py", "source_location": "L35", "weight": 1.0}, {"source": "event_stream", "target": "event_stream_deviceeventstreamview", "relation": "contains", "confidence": "EXTRACTED", "source_file": "backend/apps/biometrics/event_stream.py", "source_location": "L92", "weight": 1.0}, {"source": "event_stream_deviceeventstreamview", "target": "view", "relation": "inherits", "confidence": "EXTRACTED", "source_file": "backend/apps/biometrics/event_stream.py", "source_location": "L92", "weight": 1.0}, {"source": "event_stream_deviceeventstreamview", "target": "event_stream_deviceeventstreamview_get", "relation": "method", "confidence": "EXTRACTED", "source_file": "backend/apps/biometrics/event_stream.py", "source_location": "L93", "weight": 1.0}]}